af_process_manager/__init__.py
af_process_manager/api_client.py
af_process_manager/configuration.py
af_process_manager/rest.py
af_process_manager/api/__init__.py
af_process_manager/api/arista_flow_service_api.py
af_process_manager/api/default_api.py
af_process_manager/api/error_data_remote_iterator_rest_api.py
af_process_manager/api/exec_hist_entry_remote_iterator_rest_api.py
af_process_manager/api/execution_history_api.py
af_process_manager/api/inst_id_remote_iterator_api.py
af_process_manager/api/inst_ref_remote_iterator_rest_api.py
af_process_manager/api/inst_status_remote_iterator_rest_api.py
af_process_manager/api/instance_manager_api.py
af_process_manager/api/instance_remote_iterator_rest_api.py
af_process_manager/api/templ_id_remote_iterator_api.py
af_process_manager/api/templ_kind_remote_iterator_rest_api.py
af_process_manager/api/templ_ref_remote_iterator_rest_api.py
af_process_manager/api/templ_status_remote_iterator_rest_api.py
af_process_manager/api/template_manager_api.py
af_process_manager/api/template_remote_iterator_rest_api.py
af_process_manager/api/work_hist_entry_remote_iterator_rest_api.py
af_process_manager/models/__init__.py
af_process_manager/models/abort_service_exception.py
af_process_manager/models/abort_transaction_exception.py
af_process_manager/models/accessed_process_model_parameter.py
af_process_manager/models/activity.py
af_process_manager/models/activity_conf_extension.py
af_process_manager/models/activity_configuration.py
af_process_manager/models/af_configuration.py
af_process_manager/models/agent_locales.py
af_process_manager/models/agent_unknown_exception.py
af_process_manager/models/agent_with_time.py
af_process_manager/models/authentication_exception.py
af_process_manager/models/boolean_comparison.py
af_process_manager/models/combining_filter.py
af_process_manager/models/comparison_filter.py
af_process_manager/models/configuration_desc_entry.py
af_process_manager/models/configuration_exception.py
af_process_manager-3.0.3.dist-info/LICENSE
af_process_manager-3.0.3.dist-info/METADATA
af_process_manager-3.0.3.dist-info/WHEEL
af_process_manager-3.0.3.dist-info/top_level.txt
af_process_manager-3.0.3.dist-info/RECORD
